rlc.py
RLC-0.1.1.dist-info/LICENSE
RLC-0.1.1.dist-info/WHEEL
RLC-0.1.1.dist-info/METADATA
RLC-0.1.1.dist-info/RECORD
